cdk8s_external_dns/__init__.py
cdk8s_external_dns/py.typed
cdk8s_external_dns/_jsii/__init__.py
cdk8s_external_dns/_jsii/cdk8s-external-dns@0.0.3.jsii.tgz
cdk8s_external_dns-0.0.3.dist-info/LICENSE
cdk8s_external_dns-0.0.3.dist-info/METADATA
cdk8s_external_dns-0.0.3.dist-info/WHEEL
cdk8s_external_dns-0.0.3.dist-info/top_level.txt
cdk8s_external_dns-0.0.3.dist-info/RECORD
